{"__symbolic":"module","version":4,"metadata":{"NgRutterModule":{"__symbolic":"class","decorators":[{"__symbolic":"call","expression":{"__symbolic":"reference","module":"@angular/core","name":"NgModule","line":7,"character":1},"arguments":[{"imports":[{"__symbolic":"reference","module":"@angular/common","name":"CommonModule","line":9,"character":4}],"providers":[{"__symbolic":"reference","name":"ɵb"}],"declarations":[{"__symbolic":"reference","name":"ɵc"}],"exports":[{"__symbolic":"reference","name":"ɵc"}]}]}],"members":{},"statics":{"forRoot":{"__symbolic":"function","parameters":["options"],"value":{"ngModule":{"__symbolic":"reference","name":"NgRutterModule"},"providers":[{"provide":{"__symbolic":"reference","name":"FOR_ROOT_OPTIONS_TOKEN"},"useValue":{"__symbolic":"reference","name":"options"}},{"provide":{"__symbolic":"reference","name":"ɵa"},"useFactory":{"__symbolic":"reference","name":"provideMyServiceOptions"},"deps":[{"__symbolic":"reference","name":"FOR_ROOT_OPTIONS_TOKEN"}]}]}}}},"ModuleOptions":{"__symbolic":"interface"},"FOR_ROOT_OPTIONS_TOKEN":{"__symbolic":"new","expression":{"__symbolic":"reference","module":"@angular/core","name":"InjectionToken","line":48,"character":40},"arguments":["forRoot() MyService configuration."]},"provideMyServiceOptions":{"__symbolic":"function"},"ɵa":{"__symbolic":"class","decorators":[{"__symbolic":"call","expression":{"__symbolic":"reference","module":"@angular/core","name":"Injectable","line":19,"character":1},"arguments":[{"providedIn":"root"}]}],"members":{},"statics":{"ngInjectableDef":{}}},"ɵb":{"__symbolic":"class","decorators":[{"__symbolic":"call","expression":{"__symbolic":"reference","module":"@angular/core","name":"Injectable","line":26,"character":1},"arguments":[{"providedIn":"root"}]}],"members":{"open":[{"__symbolic":"method"}],"loadRutter":[{"__symbolic":"method"}],"setup":[{"__symbolic":"method"}],"__ctor__":[{"__symbolic":"constructor","parameters":[{"__symbolic":"reference","name":"ɵa"}]}],"destroy":[{"__symbolic":"method"}]},"statics":{"ngInjectableDef":{}}},"ɵc":{"__symbolic":"class","decorators":[{"__symbolic":"call","expression":{"__symbolic":"reference","module":"@angular/core","name":"Component","line":3,"character":1},"arguments":[{"selector":"ng-rutter","template":"<div class=\"btn\" (click)=\"load()\" \n[style.background-color]=\"backgroundColor\"\n[style.color]=\"color\"\n\n> {{ text }} </div>","styles":[".btn{display:inline-block;font-weight:400;text-align:center;white-space:nowrap;vertical-align:middle;-webkit-user-select:none;-moz-user-select:none;-ms-user-select:none;user-select:none;border:1px solid transparent;padding:.375rem .75rem;font-size:1rem;line-height:1.5;border-radius:.25rem;position:relative;color:#fff;background-color:#007bff;font-family:Lato,sans-serif!important;cursor:pointer}"]}]}],"members":{"text":[{"__symbolic":"property","decorators":[{"__symbolic":"call","expression":{"__symbolic":"reference","module":"@angular/core","name":"Input","line":14,"character":3}}]}],"backgroundColor":[{"__symbolic":"property","decorators":[{"__symbolic":"call","expression":{"__symbolic":"reference","module":"@angular/core","name":"Input","line":15,"character":3}}]}],"color":[{"__symbolic":"property","decorators":[{"__symbolic":"call","expression":{"__symbolic":"reference","module":"@angular/core","name":"Input","line":16,"character":3}}]}],"onSuccess":[{"__symbolic":"property","decorators":[{"__symbolic":"call","expression":{"__symbolic":"reference","module":"@angular/core","name":"Output","line":18,"character":3}}]}],"onLoad":[{"__symbolic":"property","decorators":[{"__symbolic":"call","expression":{"__symbolic":"reference","module":"@angular/core","name":"Output","line":19,"character":3}}]}],"onExit":[{"__symbolic":"property","decorators":[{"__symbolic":"call","expression":{"__symbolic":"reference","module":"@angular/core","name":"Output","line":20,"character":3}}]}],"load":[{"__symbolic":"method"}],"ngOnInit":[{"__symbolic":"method"}],"__ctor__":[{"__symbolic":"constructor","parameters":[{"__symbolic":"reference","name":"ɵb"}]}]}}},"origins":{"NgRutterModule":"./src/app/modules/ng-rutter/ng-rutter.module","ModuleOptions":"./src/app/modules/ng-rutter/ng-rutter.module","FOR_ROOT_OPTIONS_TOKEN":"./src/app/modules/ng-rutter/ng-rutter.module","provideMyServiceOptions":"./src/app/modules/ng-rutter/ng-rutter.module","ɵa":"./src/app/modules/ng-rutter/ng-rutter.service","ɵb":"./src/app/modules/ng-rutter/ng-rutter.service","ɵc":"./src/app/modules/ng-rutter/ng-rutter.component"},"importAs":"ng-rutter"}